setup.cfg
setup.py
django_schemas/__init__.py
django_schemas/exceptions.py
django_schemas/migrations.py
django_schemas/models.py
django_schemas/modelsfactory.py
django_schemas/routers.py
django_schemas/utils.py
django_schemas.egg-info/PKG-INFO
django_schemas.egg-info/SOURCES.txt
django_schemas.egg-info/dependency_links.txt
django_schemas.egg-info/requires.txt
django_schemas.egg-info/top_level.txt
django_schemas/backends/__init__.py
django_schemas/backends/conf.py
django_schemas/backends/postgis/__init__.py
django_schemas/backends/postgis/wrapper/__init__.py
django_schemas/backends/postgis/wrapper/base.py
django_schemas/backends/postgres/__init__.py
django_schemas/backends/postgres/wrapper/__init__.py
django_schemas/backends/postgres/wrapper/base.py
django_schemas/management/__init__.py
django_schemas/management/commands/__init__.py
django_schemas/management/commands/migrate_schema.py