Metadata-Version: 1.1
Name: django-schemas
Version: 0.2.0
Summary: Postgres schemas for Django.
Home-page: https://github.com/ryannjohnson/django-schemas
Author: UNKNOWN
Author-email: UNKNOWN
License: GNU General Public License v3.0
Platform: UNKNOWN
Classifier: Development Status :: 4 - Beta
Classifier: Environment :: Web Environment
Classifier: Framework :: Django :: 1.9
Classifier: Intended Audience :: Developers
Classifier: License :: OSI Approved :: GNU General Public License v3 (GPLv3)
Classifier: Programming Language :: Python :: 2.7
Classifier: Programming Language :: Python :: 3
Classifier: Programming Language :: Python :: 3.4
Classifier: Programming Language :: Python :: 3.5
